enviral/__init__.py
enviral/command.py
enviral/py.typed
enviral/structures.py
json_schema_env_validator-1.0.5.dist-info/METADATA
json_schema_env_validator-1.0.5.dist-info/WHEEL
json_schema_env_validator-1.0.5.dist-info/entry_points.txt
json_schema_env_validator-1.0.5.dist-info/top_level.txt
json_schema_env_validator-1.0.5.dist-info/RECORD
