Metadata-Version: 2.1
Name: json-schema-env-validator
Version: 1.0.5
Summary: UNKNOWN
Home-page: https://github.com/onna/enviral
Author: Nathan Van Gheem
Author-email: vangheem@gmail.com
License: UNKNOWN
Platform: UNKNOWN
Classifier: License :: OSI Approved :: BSD License
Classifier: Intended Audience :: Developers
Classifier: Programming Language :: Python :: 3.6
Classifier: Programming Language :: Python :: 3.7
Classifier: Topic :: Software Development :: Libraries :: Python Modules
Requires-Dist: jsonschema
